{
    "_config_name": "tatsu.settings",
    "color": {
        "palette": {
            "header": "#800000",
            "slogan": "#000000",
            "titleslogan": "#fffffe",
            "hovermenu": "#804000",
            "menutoggle": "#bcbbbb",
            "bg": "#ffffff",
            "text": "#000001",
            "link": "#0073bd",
            "borders": "#bbbbbb",
            "formfocusborder": "#43afe4",
            "primarytabs": "#586172",
            "primarytabstext": "#010000",
            "buttons": "#dee2ea",
            "footerborder": "#bbbbbc",
            "footer": "#fffeff",
            "footertext": "#000100"
        },
        "stylesheets": [
            "public://color/tatsu-3e78b54f/base.css",
            "public://color/tatsu-3e78b54f/layout.css",
            "public://color/tatsu-3e78b54f/small-text-components.css",
            "public://color/tatsu-3e78b54f/header.css",
            "public://color/tatsu-3e78b54f/footer.css",
            "public://color/tatsu-3e78b54f/menu-dropdown.css",
            "public://color/tatsu-3e78b54f/menu-toggle.css",
            "public://color/tatsu-3e78b54f/backdrop-form.css",
            "public://color/tatsu-3e78b54f/tabledrag.css",
            "public://color/tatsu-3e78b54f/vertical-tabs.css",
            "public://color/tatsu-3e78b54f/fieldset.css",
            "public://color/tatsu-3e78b54f/dialog.css",
            "public://color/tatsu-3e78b54f/progress.css",
            "public://color/tatsu-3e78b54f/admin-tabs.css",
            "public://color/tatsu-3e78b54f/breadcrumb.css",
            "public://color/tatsu-3e78b54f/pager.css",
            "public://color/tatsu-3e78b54f/hero.css",
            "public://color/tatsu-3e78b54f/teasers.css",
            "public://color/tatsu-3e78b54f/comment.css",
            "public://color/tatsu-3e78b54f/caption.css",
            "public://color/tatsu-3e78b54f/skin.css"
        ],
        "files": [
            "public://color/tatsu-3e78b54f/base.css",
            "public://color/tatsu-3e78b54f/layout.css",
            "public://color/tatsu-3e78b54f/small-text-components.css",
            "public://color/tatsu-3e78b54f/header.css",
            "public://color/tatsu-3e78b54f/footer.css",
            "public://color/tatsu-3e78b54f/menu-dropdown.css",
            "public://color/tatsu-3e78b54f/menu-toggle.css",
            "public://color/tatsu-3e78b54f/backdrop-form.css",
            "public://color/tatsu-3e78b54f/tabledrag.css",
            "public://color/tatsu-3e78b54f/vertical-tabs.css",
            "public://color/tatsu-3e78b54f/fieldset.css",
            "public://color/tatsu-3e78b54f/dialog.css",
            "public://color/tatsu-3e78b54f/progress.css",
            "public://color/tatsu-3e78b54f/admin-tabs.css",
            "public://color/tatsu-3e78b54f/breadcrumb.css",
            "public://color/tatsu-3e78b54f/pager.css",
            "public://color/tatsu-3e78b54f/hero.css",
            "public://color/tatsu-3e78b54f/teasers.css",
            "public://color/tatsu-3e78b54f/comment.css",
            "public://color/tatsu-3e78b54f/caption.css",
            "public://color/tatsu-3e78b54f/skin.css"
        ]
    }
}
